testcontainer_python_keycloak/__init__.py
testcontainer_python_keycloak/keycloak.py
testcontainer_python_keycloak-0.3.0.dist-info/LICENSE
testcontainer_python_keycloak-0.3.0.dist-info/WHEEL
testcontainer_python_keycloak-0.3.0.dist-info/METADATA
testcontainer_python_keycloak-0.3.0.dist-info/RECORD
