Metadata-Version: 2.1
Name: testcontainer-python-keycloak
Version: 0.3.0
Summary: 
Author: Max Fröhlich
Author-email: max.froehlich@serviceware.de
Requires-Python: >=3.8,<4.0
Classifier: Programming Language :: Python :: 3
Classifier: Programming Language :: Python :: 3.10
Classifier: Programming Language :: Python :: 3.8
Classifier: Programming Language :: Python :: 3.9
Requires-Dist: testcontainers (>=3.0.0,<4.0.0)
